weather_test_mcp/__init__.py
weather_test_mcp/main.py
holyblue_weather_test_mcp-0.1.1.dist-info/METADATA
holyblue_weather_test_mcp-0.1.1.dist-info/WHEEL
holyblue_weather_test_mcp-0.1.1.dist-info/entry_points.txt
holyblue_weather_test_mcp-0.1.1.dist-info/top_level.txt
holyblue_weather_test_mcp-0.1.1.dist-info/RECORD
